deccom/__init__.py
deccom-0.0.1.dist-info/LICENSE
deccom-0.0.1.dist-info/METADATA
deccom-0.0.1.dist-info/WHEEL
deccom-0.0.1.dist-info/top_level.txt
deccom-0.0.1.dist-info/RECORD
