Metadata-Version: 2.1
Name: deccom
Version: 0.0.1
Summary: Decentralized Communication With Modular Protocol Stack.
Home-page: https://github.com/NikolayBlagoev/DecCom-Python
Author: Nikolay Blagoev
Author-email: nickyblagoev@gmail.com
License: MIT
Classifier: Intended Audience :: Developers
Classifier: License :: OSI Approved :: MIT License
Classifier: Operating System :: OS Independent
Classifier: Programming Language :: Python
Classifier: Programming Language :: Python :: 3
License-File: LICENSE
Requires-Dist: cryptography
Requires-Dist: fe25519
Requires-Dist: ge25519
